common_interfaces/_dummy.cpython-310-x86_64-linux-gnu.so
ros_common_interfaces-5.5.1.data/data/share/ament_index/resource_index/package_run_dependencies/common_interfaces
ros_common_interfaces-5.5.1.data/data/share/ament_index/resource_index/packages/common_interfaces
ros_common_interfaces-5.5.1.data/data/share/ament_index/resource_index/parent_prefix_path/common_interfaces
ros_common_interfaces-5.5.1.data/data/share/common_interfaces/local_setup.bash
ros_common_interfaces-5.5.1.data/data/share/common_interfaces/local_setup.dsv
ros_common_interfaces-5.5.1.data/data/share/common_interfaces/local_setup.sh
ros_common_interfaces-5.5.1.data/data/share/common_interfaces/local_setup.zsh
ros_common_interfaces-5.5.1.data/data/share/common_interfaces/package.dsv
ros_common_interfaces-5.5.1.data/data/share/common_interfaces/package.xml
ros_common_interfaces-5.5.1.data/data/share/common_interfaces/cmake/common_interfacesConfig-version.cmake
ros_common_interfaces-5.5.1.data/data/share/common_interfaces/cmake/common_interfacesConfig.cmake
ros_common_interfaces-5.5.1.data/data/share/common_interfaces/environment/ament_prefix_path.dsv
ros_common_interfaces-5.5.1.data/data/share/common_interfaces/environment/ament_prefix_path.sh
ros_common_interfaces-5.5.1.data/data/share/common_interfaces/environment/path.dsv
ros_common_interfaces-5.5.1.data/data/share/common_interfaces/environment/path.sh
ros_common_interfaces-5.5.1.dist-info/METADATA
ros_common_interfaces-5.5.1.dist-info/WHEEL
ros_common_interfaces-5.5.1.dist-info/top_level.txt
ros_common_interfaces-5.5.1.dist-info/RECORD
ros_common_interfaces-5.5.1.dist-info/licenses/LICENSE
