Metadata-Version: 2.4
Name: ros-common-interfaces
Version: 5.5.1
Summary: Wheel for the common_interfaces (ros-common-interfaces) ROS 2 package.
License-File: LICENSE
Requires-Dist: ros-std-srvs~=5.5.1
Requires-Dist: ros-shape-msgs~=5.5.1
Requires-Dist: ros-actionlib-msgs~=5.5.1
Requires-Dist: ros-stereo-msgs~=5.5.1
Requires-Dist: ros-geometry-msgs~=5.5.1
Requires-Dist: ros-builtin-interfaces~=2.3.0
Requires-Dist: ros-trajectory-msgs~=5.5.1
Requires-Dist: ros-nav-msgs~=5.5.1
Requires-Dist: ros-diagnostic-msgs~=5.5.1
Requires-Dist: ros-sensor-msgs~=5.5.1
Requires-Dist: ros-std-msgs~=5.5.1
Requires-Dist: ros-visualization-msgs~=5.5.1
Dynamic: description
Dynamic: description-content-type
Dynamic: license-file
Dynamic: requires-dist
Dynamic: summary
